esgcet/__init__.py
esgcet/activity_check.py
esgcet/args.py
esgcet/cmip5.py
esgcet/cmip6.py
esgcet/create_ip.py
esgcet/e3sm.py
esgcet/esgindexpub.py
esgcet/esgmapconv.py
esgcet/esgmigrate.py
esgcet/esgmkpubrec.py
esgcet/esgpidcitepub.py
esgcet/esgunpublish.py
esgcet/esgupdate.py
esgcet/generic_netcdf.py
esgcet/generic_pub.py
esgcet/globus_query.py
esgcet/globus_search.py
esgcet/handler_base.py
esgcet/index_pub.py
esgcet/input4mips.py
esgcet/list2json.py
esgcet/logger.py
esgcet/mapfile.py
esgcet/migratecmd.py
esgcet/mk_dataset.py
esgcet/mk_dataset_autoc.py
esgcet/mk_dataset_nc4.py
esgcet/mk_dataset_xarray.py
esgcet/mkd_cmip5.py
esgcet/mkd_create_ip.py
esgcet/mkd_input4mips.py
esgcet/mkd_non_nc.py
esgcet/pid_cite_pub.py
esgcet/pub_client.py
esgcet/pub_internal.py
esgcet/pub_test.py
esgcet/publish_script.py
esgcet/search_check.py
esgcet/settings.py
esgcet/unpublish_globus.py
esgcet/unpublish_solr.py
esgcet/update.py
esgcet/update_base.py
esgcet/update_globus.py
esgcet/update_solr.py
esgcet/xmlfix.py
esgcet/test/test_update.py
esgcet-5.3.5.dist-info/METADATA
esgcet-5.3.5.dist-info/WHEEL
esgcet-5.3.5.dist-info/entry_points.txt
esgcet-5.3.5.dist-info/top_level.txt
esgcet-5.3.5.dist-info/RECORD
