Metadata-Version: 2.4
Name: esgcet
Version: 5.3.5
Summary: ESGCET publication package
Home-page: http://esgf.github.io
Author: Sasha Ames
Author-email: ames4@llnl.gov
Requires-Dist: requests
Requires-Dist: esgfpid
Requires-Dist: ESGConfigParser==1.0.0a1
Requires-Dist: xarray
Requires-Dist: netcdf4
Requires-Dist: dask
Requires-Dist: pyyaml
Requires-Dist: globus-cli
Dynamic: author
Dynamic: author-email
Dynamic: home-page
Dynamic: requires-dist
Dynamic: summary
